{
  "projects": [
    {
      "id": 1,
      "name": "Omnifood clone",
      "description": "A simple web app to track and reset scores between two players with a set winning score.",
      "link": "https://omnifood-project-gamma.vercel.app"
    },
    {
      "id": 2,
      "name": "Score keeper",
      "description": "A subscription-based meal delivery service offering personalized weekly meal plans, chef-prepared healthy dishes, and daily delivery — tailored to dietary preferences, fully customizable, with flexible plans.",
      "link": "https://score-keeper-sable.vercel.app"
    },
    {
      "id": 3,
      "name": "Todo List",
      "description": "A simple task management application built with React, Not used Node.js, Express, and MongoDB (MERN stack) but I have stored the data in localStorage. Users can add, edit, and delete tasks. Hosted on Vercel for easy deployment.",
      "link": "https://todo-list-six-sandy.vercel.app"
    }
  ]
}
